matic/__init__.py
matic/app.py
matic/cli.py
matic/components/__init__.py
matic/components/cmd_input.py
matic/components/cmd_log.py
matic/components/history.py
matic/components/history_table.py
matic/components/res_highlighter.py
matic/dom.tcss
matic/output_manager.py
stat_o_matic-0.2.1.dist-info/METADATA
stat_o_matic-0.2.1.dist-info/WHEEL
stat_o_matic-0.2.1.dist-info/entry_points.txt
stat_o_matic-0.2.1.dist-info/RECORD
